MANIFEST.in
README.rst
setup.cfg
setup.py
docs/HISTORY.txt
docs/LICENSE.GPL
docs/LICENSE.txt
src/Allanon.egg-info/PKG-INFO
src/Allanon.egg-info/SOURCES.txt
src/Allanon.egg-info/dependency_links.txt
src/Allanon.egg-info/entry_points.txt
src/Allanon.egg-info/not-zip-safe
src/Allanon.egg-info/requires.txt
src/Allanon.egg-info/top_level.txt
src/allanon/__init__.py
src/allanon/config.py
src/allanon/html_crawler.py
src/allanon/main.py
src/allanon/resouce_grabber.py
src/allanon/url_generator.py
src/allanon/version.txt
src/allanon/tests/__init__.py
src/allanon/tests/acceptance_tests.py
src/allanon/tests/html_crawler_tests.py
src/allanon/tests/resource_grabber_tests.py
src/allanon/tests/url_generator_tests.py
src/allanon/tests/data/image1.png
src/allanon/tests/data/notfound.html
src/allanon/tests/data/page.html
src/allanon/tests/data/page1.html
src/allanon/tests/data/page2.html
src/allanon/tests/data/text1.txt
src/allanon/tests/data/text2.txt