Metadata-Version: 1.1
Name: Allanon
Version: 0.2
Summary: A Web crawler that visit a predictable set of URLs, and automatically download resources you want from them
Home-page: https://github.com/keul/Allanon
Author: keul
Author-email: luca@keul.it
License: GPL
Keywords: crawler robot spider downloader parser
Platform: UNKNOWN
Classifier: Development Status :: 3 - Alpha
Classifier: License :: OSI Approved :: GNU General Public License (GPL)
Classifier: Operating System :: OS Independent
Classifier: Programming Language :: Python
Classifier: Topic :: Utilities
Classifier: Topic :: System :: Shells
Classifier: Topic :: Internet :: WWW/HTTP
Classifier: Programming Language :: Python
Classifier: Programming Language :: Python :: 2.7
